typed_dotenv/__init__.py
typed_dotenv-2.0.2.dist-info/METADATA
typed_dotenv-2.0.2.dist-info/WHEEL
typed_dotenv-2.0.2.dist-info/RECORD
