Metadata-Version: 2.1
Name: typed_dotenv
Version: 2.0.2
Summary: Handle .env files with types
Home-page: https://github.com/ewen-lbh/python-typed-dotenv
License: MIT
Author: Ewen Le Bihan
Author-email: hey@ewen.works
Requires-Python: >=3.8
Classifier: License :: OSI Approved :: MIT License
Classifier: Programming Language :: Python :: 3
Classifier: Programming Language :: Python :: 3.8
Classifier: Programming Language :: Python :: 3.9
Classifier: Programming Language :: Python :: 3.10
Classifier: Programming Language :: Python :: 3.11
Classifier: Programming Language :: Python :: 3.12
Provides-Extra: all
Provides-Extra: pydantic
Provides-Extra: toml
Provides-Extra: yaml
Requires-Dist: parse (>=1.16.0,<2.0.0)
Requires-Dist: pydantic (>=1.6.1,<2.0.0) ; extra == "pydantic" or extra == "all"
Requires-Dist: python-dotenv (>=0.14.0,<0.15.0)
Requires-Dist: ruamel.yaml (>=0.16.10,<0.17.0) ; extra == "yaml" or extra == "all"
Requires-Dist: toml (>=0.10.1,<0.11.0) ; extra == "toml" or extra == "all"
Project-URL: Repository, https://github.com/ewen-lbh/python-typed-dotenv
